solidity_typestub/__init__.py
solidity_typestub/printer.py
solidity_typestub/solidity_types.py
solidity_typestub-0.0.1.dist-info/LICENSE.md
solidity_typestub-0.0.1.dist-info/METADATA
solidity_typestub-0.0.1.dist-info/WHEEL
solidity_typestub-0.0.1.dist-info/entry_points.txt
solidity_typestub-0.0.1.dist-info/top_level.txt
solidity_typestub-0.0.1.dist-info/zip-safe
solidity_typestub-0.0.1.dist-info/RECORD
