Metadata-Version: 2.1
Name: solidity-typestub
Version: 0.0.1
Summary: Generate python typestubs for abi of solidity contracts
Home-page: https://github.com/jO-Osko/solidity-stubgen
Author: Filip Koprivec
Author-email: koprivec.filip@gmail.com
License: MIT
Keywords: solidity abi workflow mypy typestubs
Platform: UNKNOWN
Classifier: Development Status :: 3 - Alpha
Classifier: Environment :: Console
Classifier: Intended Audience :: Developers
Classifier: License :: OSI Approved :: MIT License
Classifier: Operating System :: OS Independent
Classifier: Programming Language :: Python
Classifier: Programming Language :: Python :: 3.7
Classifier: Programming Language :: Python :: 3.8
Classifier: Programming Language :: Python :: 3.9
Classifier: Programming Language :: Python :: 3.10
Classifier: Programming Language :: Python :: 3 :: Only
Classifier: Topic :: Software Development :: Libraries :: Python Modules
Requires-Python: >=3.7.0
Requires-Dist: black
